[{"station_code": "G4931", "station_name": "Cestos River At Iti 08Ce001", "lat": 5.617, "lon": -9.319, "pcodes": {"1": ["LR15", "LR14", "LR12", "LR06"], "2": []}, "thresholds": [{"return_period": 1.5, "threshold_value": 1057.6350805565987}, {"return_period": 2.0, "threshold_value": 1245.1958118130701}, {"return_period": 5.0, "threshold_value": 1706.7775036741268}, {"return_period": 10.0, "threshold_value": 2012.384747234395}, {"return_period": 20.0, "threshold_value": 2305.5305524437936}, {"return_period": 50.0, "threshold_value": 2684.9777280859207}, {"return_period": 100.0, "threshold_value": 2969.319989937473}, {"return_period": 200.0, "threshold_value": 3252.624734638536}, {"return_period": 500.0, "threshold_value": 3626.3915500160856}]}, {"station_code": "G4931", "station_name": "Cestos River At Iti 08Ce001", "lat": 5.617, "lon": -9.319, "pcodes": {"1": ["LR15", "LR14", "LR12", "LR06"], "2": []}, "thresholds": [{"return_period": 1.5, "threshold_value": 1057.6350805565987}, {"return_period": 2.0, "threshold_value": 1245.1958118130701}, {"return_period": 5.0, "threshold_value": 1706.7775036741268}, {"return_period": 10.0, "threshold_value": 2012.384747234395}, {"return_period": 20.0, "threshold_value": 2305.5305524437936}, {"return_period": 50.0, "threshold_value": 2684.9777280859207}, {"return_period": 100.0, "threshold_value": 2969.319989937473}, {"return_period": 200.0, "threshold_value": 3252.624734638536}, {"return_period": 500.0, "threshold_value": 3626.3915500160856}]}, {"station_code": "G4931", "station_name": "Cestos River At Iti 08Ce001", "lat": 5.617, "lon": -9.319, "pcodes": {"1": ["LR15", "LR14", "LR12", "LR06"], "2": []}, "thresholds": [{"return_period": 1.5, "threshold_value": 1057.6350805565987}, {"return_period": 2.0, "threshold_value": 1245.1958118130701}, {"return_period": 5.0, "threshold_value": 1706.7775036741268}, {"return_period": 10.0, "threshold_value": 2012.384747234395}, {"return_period": 20.0, "threshold_value": 2305.5305524437936}, {"return_period": 50.0, "threshold_value": 2684.9777280859207}, {"return_period": 100.0, "threshold_value": 2969.319989937473}, {"return_period": 200.0, "threshold_value": 3252.624734638536}, {"return_period": 500.0, "threshold_value": 3626.3915500160856}]}, {"station_code": "G4931", "station_name": "Cestos River At Iti 08Ce001", "lat": 5.617, "lon": -9.319, "pcodes": {"1": ["LR15", "LR14", "LR12", "LR06"], "2": []}, "thresholds": [{"return_period": 1.5, "threshold_value": 1057.6350805565987}, {"return_period": 2.0, "threshold_value": 1245.1958118130701}, {"return_period": 5.0, "threshold_value": 1706.7775036741268}, {"return_period": 10.0, "threshold_value": 2012.384747234395}, {"return_period": 20.0, "threshold_value": 2305.5305524437936}, {"return_period": 50.0, "threshold_value": 2684.9777280859207}, {"return_period": 100.0, "threshold_value": 2969.319989937473}, {"return_period": 200.0, "threshold_value": 3252.624734638536}, {"return_period": 500.0, "threshold_value": 3626.3915500160856}]}, {"station_code": "G4931", "station_name": "Cestos River At Iti 08Ce001", "lat": 5.617, "lon": -9.319, "pcodes": {"1": ["LR15", "LR14", "LR12", "LR06"], "2": []}, "thresholds": [{"return_period": 1.5, "threshold_value": 1057.6350805565987}, {"return_period": 2.0, "threshold_value": 1245.1958118130701}, {"return_period": 5.0, "threshold_value": 1706.7775036741268}, {"return_period": 10.0, "threshold_value": 2012.384747234395}, {"return_period": 20.0, "threshold_value": 2305.5305524437936}, {"return_period": 50.0, "threshold_value": 2684.9777280859207}, {"return_period": 100.0, "threshold_value": 2969.319989937473}, {"return_period": 200.0, "threshold_value": 3252.624734638536}, {"return_period": 500.0, "threshold_value": 3626.3915500160856}]}, {"station_code": "G4931", "station_name": "Cestos River At Iti 08Ce001", "lat": 5.617, "lon": -9.319, "pcodes": {"1": ["LR15", "LR14", "LR12", "LR06"], "2": []}, "thresholds": [{"return_period": 1.5, "threshold_value": 1057.6350805565987}, {"return_period": 2.0, "threshold_value": 1245.1958118130701}, {"return_period": 5.0, "threshold_value": 1706.7775036741268}, {"return_period": 10.0, "threshold_value": 2012.384747234395}, {"return_period": 20.0, "threshold_value": 2305.5305524437936}, {"return_period": 50.0, "threshold_value": 2684.9777280859207}, {"return_period": 100.0, "threshold_value": 2969.319989937473}, {"return_period": 200.0, "threshold_value": 3252.624734638536}, {"return_period": 500.0, "threshold_value": 3626.3915500160856}]}, {"station_code": "G4931", "station_name": "Cestos River At Iti 08Ce001", "lat": 5.617, "lon": -9.319, "pcodes": {"1": ["LR15", "LR14", "LR12", "LR06"], "2": []}, "thresholds": [{"return_period": 1.5, "threshold_value": 1057.6350805565987}, {"return_period": 2.0, "threshold_value": 1245.1958118130701}, {"return_period": 5.0, "threshold_value": 1706.7775036741268}, {"return_period": 10.0, "threshold_value": 2012.384747234395}, {"return_period": 20.0, "threshold_value": 2305.5305524437936}, {"return_period": 50.0, "threshold_value": 2684.9777280859207}, {"return_period": 100.0, "threshold_value": 2969.319989937473}, {"return_period": 200.0, "threshold_value": 3252.624734638536}, {"return_period": 500.0, "threshold_value": 3626.3915500160856}]}, {"station_code": "G4947", "station_name": "Lofa Bridge 03Lo001", "lat": 7.067, "lon": -10.88, "pcodes": {"1": ["LR01", "LR08", "LR03", "LR05"], "2": []}, "thresholds": [{"return_period": 1.5, "threshold_value": 993.1359230582627}, {"return_period": 2.0, "threshold_value": 1091.3516046622226}, {"return_period": 5.0, "threshold_value": 1333.0576386403689}, {"return_period": 10.0, "threshold_value": 1493.0880646698763}, {"return_period": 20.0, "threshold_value": 1646.5930914156565}, {"return_period": 50.0, "threshold_value": 1845.2896028801429}, {"return_period": 100.0, "threshold_value": 1994.1846773953653}, {"return_period": 200.0, "threshold_value": 2142.5364587946533}, {"return_period": 500.0, "threshold_value": 2338.2584646075347}]}, {"station_code": "G4947", "station_name": "Lofa Bridge 03Lo001", "lat": 7.067, "lon": -10.88, "pcodes": {"1": ["LR01", "LR08", "LR03", "LR05"], "2": []}, "thresholds": [{"return_period": 1.5, "threshold_value": 993.1359230582627}, {"return_period": 2.0, "threshold_value": 1091.3516046622226}, {"return_period": 5.0, "threshold_value": 1333.0576386403689}, {"return_period": 10.0, "threshold_value": 1493.0880646698763}, {"return_period": 20.0, "threshold_value": 1646.5930914156565}, {"return_period": 50.0, "threshold_value": 1845.2896028801429}, {"return_period": 100.0, "threshold_value": 1994.1846773953653}, {"return_period": 200.0, "threshold_value": 2142.5364587946533}, {"return_period": 500.0, "threshold_value": 2338.2584646075347}]}, {"station_code": "G4947", "station_name": "Lofa Bridge 03Lo001", "lat": 7.067, "lon": -10.88, "pcodes": {"1": ["LR01", "LR08", "LR03", "LR05"], "2": []}, "thresholds": [{"return_period": 1.5, "threshold_value": 993.1359230582627}, {"return_period": 2.0, "threshold_value": 1091.3516046622226}, {"return_period": 5.0, "threshold_value": 1333.0576386403689}, {"return_period": 10.0, "threshold_value": 1493.0880646698763}, {"return_period": 20.0, "threshold_value": 1646.5930914156565}, {"return_period": 50.0, "threshold_value": 1845.2896028801429}, {"return_period": 100.0, "threshold_value": 1994.1846773953653}, {"return_period": 200.0, "threshold_value": 2142.5364587946533}, {"return_period": 500.0, "threshold_value": 2338.2584646075347}]}, {"station_code": "G4947", "station_name": "Lofa Bridge 03Lo001", "lat": 7.067, "lon": -10.88, "pcodes": {"1": ["LR01", "LR08", "LR03", "LR05"], "2": []}, "thresholds": [{"return_period": 1.5, "threshold_value": 993.1359230582627}, {"return_period": 2.0, "threshold_value": 1091.3516046622226}, {"return_period": 5.0, "threshold_value": 1333.0576386403689}, {"return_period": 10.0, "threshold_value": 1493.0880646698763}, {"return_period": 20.0, "threshold_value": 1646.5930914156565}, {"return_period": 50.0, "threshold_value": 1845.2896028801429}, {"return_period": 100.0, "threshold_value": 1994.1846773953653}, {"return_period": 200.0, "threshold_value": 2142.5364587946533}, {"return_period": 500.0, "threshold_value": 2338.2584646075347}]}, {"station_code": "G4947", "station_name": "Lofa Bridge 03Lo001", "lat": 7.067, "lon": -10.88, "pcodes": {"1": ["LR01", "LR08", "LR03", "LR05"], "2": []}, "thresholds": [{"return_period": 1.5, "threshold_value": 993.1359230582627}, {"return_period": 2.0, "threshold_value": 1091.3516046622226}, {"return_period": 5.0, "threshold_value": 1333.0576386403689}, {"return_period": 10.0, "threshold_value": 1493.0880646698763}, {"return_period": 20.0, "threshold_value": 1646.5930914156565}, {"return_period": 50.0, "threshold_value": 1845.2896028801429}, {"return_period": 100.0, "threshold_value": 1994.1846773953653}, {"return_period": 200.0, "threshold_value": 2142.5364587946533}, {"return_period": 500.0, "threshold_value": 2338.2584646075347}]}, {"station_code": "G4947", "station_name": "Lofa Bridge 03Lo001", "lat": 7.067, "lon": -10.88, "pcodes": {"1": ["LR01", "LR08", "LR03", "LR05"], "2": []}, "thresholds": [{"return_period": 1.5, "threshold_value": 993.1359230582627}, {"return_period": 2.0, "threshold_value": 1091.3516046622226}, {"return_period": 5.0, "threshold_value": 1333.0576386403689}, {"return_period": 10.0, "threshold_value": 1493.0880646698763}, {"return_period": 20.0, "threshold_value": 1646.5930914156565}, {"return_period": 50.0, "threshold_value": 1845.2896028801429}, {"return_period": 100.0, "threshold_value": 1994.1846773953653}, {"return_period": 200.0, "threshold_value": 2142.5364587946533}, {"return_period": 500.0, "threshold_value": 2338.2584646075347}]}, {"station_code": "G4947", "station_name": "Lofa Bridge 03Lo001", "lat": 7.067, "lon": -10.88, "pcodes": {"1": ["LR01", "LR08", "LR03", "LR05"], "2": []}, "thresholds": [{"return_period": 1.5, "threshold_value": 993.1359230582627}, {"return_period": 2.0, "threshold_value": 1091.3516046622226}, {"return_period": 5.0, "threshold_value": 1333.0576386403689}, {"return_period": 10.0, "threshold_value": 1493.0880646698763}, {"return_period": 20.0, "threshold_value": 1646.5930914156565}, {"return_period": 50.0, "threshold_value": 1845.2896028801429}, {"return_period": 100.0, "threshold_value": 1994.1846773953653}, {"return_period": 200.0, "threshold_value": 2142.5364587946533}, {"return_period": 500.0, "threshold_value": 2338.2584646075347}]}, {"station_code": "G4948", "station_name": "Kaiha At Kolba 01Ma001", "lat": 8.278, "lon": -10.078, "pcodes": {"1": ["LR05", "LR08", "LR03"], "2": []}, "thresholds": [{"return_period": 1.5, "threshold_value": 73.65828189259027}, {"return_period": 2.0, "threshold_value": 82.1336935959261}, {"return_period": 5.0, "threshold_value": 102.99144376056663}, {"return_period": 10.0, "threshold_value": 116.80108926228482}, {"return_period": 20.0, "threshold_value": 130.04763277707946}, {"return_period": 50.0, "threshold_value": 147.1939246031519}, {"return_period": 100.0, "threshold_value": 160.04265747866148}, {"return_period": 200.0, "threshold_value": 172.844507486202}, {"return_period": 500.0, "threshold_value": 189.7341176948429}]}, {"station_code": "G4948", "station_name": "Kaiha At Kolba 01Ma001", "lat": 8.278, "lon": -10.078, "pcodes": {"1": ["LR05", "LR08", "LR03"], "2": []}, "thresholds": [{"return_period": 1.5, "threshold_value": 73.65828189259027}, {"return_period": 2.0, "threshold_value": 82.1336935959261}, {"return_period": 5.0, "threshold_value": 102.99144376056663}, {"return_period": 10.0, "threshold_value": 116.80108926228482}, {"return_period": 20.0, "threshold_value": 130.04763277707946}, {"return_period": 50.0, "threshold_value": 147.1939246031519}, {"return_period": 100.0, "threshold_value": 160.04265747866148}, {"return_period": 200.0, "threshold_value": 172.844507486202}, {"return_period": 500.0, "threshold_value": 189.7341176948429}]}, {"station_code": "G4948", "station_name": "Kaiha At Kolba 01Ma001", "lat": 8.278, "lon": -10.078, "pcodes": {"1": ["LR05", "LR08", "LR03"], "2": []}, "thresholds": [{"return_period": 1.5, "threshold_value": 73.65828189259027}, {"return_period": 2.0, "threshold_value": 82.1336935959261}, {"return_period": 5.0, "threshold_value": 102.99144376056663}, {"return_period": 10.0, "threshold_value": 116.80108926228482}, {"return_period": 20.0, "threshold_value": 130.04763277707946}, {"return_period": 50.0, "threshold_value": 147.1939246031519}, {"return_period": 100.0, "threshold_value": 160.04265747866148}, {"return_period": 200.0, "threshold_value": 172.844507486202}, {"return_period": 500.0, "threshold_value": 189.7341176948429}]}, {"station_code": "G4948", "station_name": "Kaiha At Kolba 01Ma001", "lat": 8.278, "lon": -10.078, "pcodes": {"1": ["LR05", "LR08", "LR03"], "2": []}, "thresholds": [{"return_period": 1.5, "threshold_value": 73.65828189259027}, {"return_period": 2.0, "threshold_value": 82.1336935959261}, {"return_period": 5.0, "threshold_value": 102.99144376056663}, {"return_period": 10.0, "threshold_value": 116.80108926228482}, {"return_period": 20.0, "threshold_value": 130.04763277707946}, {"return_period": 50.0, "threshold_value": 147.1939246031519}, {"return_period": 100.0, "threshold_value": 160.04265747866148}, {"return_period": 200.0, "threshold_value": 172.844507486202}, {"return_period": 500.0, "threshold_value": 189.7341176948429}]}, {"station_code": "G4948", "station_name": "Kaiha At Kolba 01Ma001", "lat": 8.278, "lon": -10.078, "pcodes": {"1": ["LR05", "LR08", "LR03"], "2": []}, "thresholds": [{"return_period": 1.5, "threshold_value": 73.65828189259027}, {"return_period": 2.0, "threshold_value": 82.1336935959261}, {"return_period": 5.0, "threshold_value": 102.99144376056663}, {"return_period": 10.0, "threshold_value": 116.80108926228482}, {"return_period": 20.0, "threshold_value": 130.04763277707946}, {"return_period": 50.0, "threshold_value": 147.1939246031519}, {"return_period": 100.0, "threshold_value": 160.04265747866148}, {"return_period": 200.0, "threshold_value": 172.844507486202}, {"return_period": 500.0, "threshold_value": 189.7341176948429}]}, {"station_code": "G4948", "station_name": "Kaiha At Kolba 01Ma001", "lat": 8.278, "lon": -10.078, "pcodes": {"1": ["LR05", "LR08", "LR03"], "2": []}, "thresholds": [{"return_period": 1.5, "threshold_value": 73.65828189259027}, {"return_period": 2.0, "threshold_value": 82.1336935959261}, {"return_period": 5.0, "threshold_value": 102.99144376056663}, {"return_period": 10.0, "threshold_value": 116.80108926228482}, {"return_period": 20.0, "threshold_value": 130.04763277707946}, {"return_period": 50.0, "threshold_value": 147.1939246031519}, {"return_period": 100.0, "threshold_value": 160.04265747866148}, {"return_period": 200.0, "threshold_value": 172.844507486202}, {"return_period": 500.0, "threshold_value": 189.7341176948429}]}, {"station_code": "G4948", "station_name": "Kaiha At Kolba 01Ma001", "lat": 8.278, "lon": -10.078, "pcodes": {"1": ["LR05", "LR08", "LR03"], "2": []}, "thresholds": [{"return_period": 1.5, "threshold_value": 73.65828189259027}, {"return_period": 2.0, "threshold_value": 82.1336935959261}, {"return_period": 5.0, "threshold_value": 102.99144376056663}, {"return_period": 10.0, "threshold_value": 116.80108926228482}, {"return_period": 20.0, "threshold_value": 130.04763277707946}, {"return_period": 50.0, "threshold_value": 147.1939246031519}, {"return_period": 100.0, "threshold_value": 160.04265747866148}, {"return_period": 200.0, "threshold_value": 172.844507486202}, {"return_period": 500.0, "threshold_value": 189.7341176948429}]}, {"station_code": "G5111", "station_name": "Mano Kongo 01Ma003", "lat": 7.328, "lon": -11.143, "pcodes": {"1": ["LR05"], "2": []}, "thresholds": [{"return_period": 1.5, "threshold_value": 750.5859679134564}, {"return_period": 2.0, "threshold_value": 844.3677500540222}, {"return_period": 5.0, "threshold_value": 1075.1620819816112}, {"return_period": 10.0, "threshold_value": 1227.9680117951257}, {"return_period": 20.0, "threshold_value": 1374.5431283208563}, {"return_period": 50.0, "threshold_value": 1564.2695818356037}, {"return_period": 100.0, "threshold_value": 1706.442860195532}, {"return_period": 200.0, "threshold_value": 1848.0973721445887}, {"return_period": 500.0, "threshold_value": 2034.9836026273404}]}, {"station_code": "G5111", "station_name": "Mano Kongo 01Ma003", "lat": 7.328, "lon": -11.143, "pcodes": {"1": ["LR05"], "2": []}, "thresholds": [{"return_period": 1.5, "threshold_value": 750.5859679134564}, {"return_period": 2.0, "threshold_value": 844.3677500540222}, {"return_period": 5.0, "threshold_value": 1075.1620819816112}, {"return_period": 10.0, "threshold_value": 1227.9680117951257}, {"return_period": 20.0, "threshold_value": 1374.5431283208563}, {"return_period": 50.0, "threshold_value": 1564.2695818356037}, {"return_period": 100.0, "threshold_value": 1706.442860195532}, {"return_period": 200.0, "threshold_value": 1848.0973721445887}, {"return_period": 500.0, "threshold_value": 2034.9836026273404}]}, {"station_code": "G5111", "station_name": "Mano Kongo 01Ma003", "lat": 7.328, "lon": -11.143, "pcodes": {"1": ["LR05"], "2": []}, "thresholds": [{"return_period": 1.5, "threshold_value": 750.5859679134564}, {"return_period": 2.0, "threshold_value": 844.3677500540222}, {"return_period": 5.0, "threshold_value": 1075.1620819816112}, {"return_period": 10.0, "threshold_value": 1227.9680117951257}, {"return_period": 20.0, "threshold_value": 1374.5431283208563}, {"return_period": 50.0, "threshold_value": 1564.2695818356037}, {"return_period": 100.0, "threshold_value": 1706.442860195532}, {"return_period": 200.0, "threshold_value": 1848.0973721445887}, {"return_period": 500.0, "threshold_value": 2034.9836026273404}]}, {"station_code": "G5111", "station_name": "Mano Kongo 01Ma003", "lat": 7.328, "lon": -11.143, "pcodes": {"1": ["LR05"], "2": []}, "thresholds": [{"return_period": 1.5, "threshold_value": 750.5859679134564}, {"return_period": 2.0, "threshold_value": 844.3677500540222}, {"return_period": 5.0, "threshold_value": 1075.1620819816112}, {"return_period": 10.0, "threshold_value": 1227.9680117951257}, {"return_period": 20.0, "threshold_value": 1374.5431283208563}, {"return_period": 50.0, "threshold_value": 1564.2695818356037}, {"return_period": 100.0, "threshold_value": 1706.442860195532}, {"return_period": 200.0, "threshold_value": 1848.0973721445887}, {"return_period": 500.0, "threshold_value": 2034.9836026273404}]}, {"station_code": "G5111", "station_name": "Mano Kongo 01Ma003", "lat": 7.328, "lon": -11.143, "pcodes": {"1": ["LR05"], "2": []}, "thresholds": [{"return_period": 1.5, "threshold_value": 750.5859679134564}, {"return_period": 2.0, "threshold_value": 844.3677500540222}, {"return_period": 5.0, "threshold_value": 1075.1620819816112}, {"return_period": 10.0, "threshold_value": 1227.9680117951257}, {"return_period": 20.0, "threshold_value": 1374.5431283208563}, {"return_period": 50.0, "threshold_value": 1564.2695818356037}, {"return_period": 100.0, "threshold_value": 1706.442860195532}, {"return_period": 200.0, "threshold_value": 1848.0973721445887}, {"return_period": 500.0, "threshold_value": 2034.9836026273404}]}, {"station_code": "G5111", "station_name": "Mano Kongo 01Ma003", "lat": 7.328, "lon": -11.143, "pcodes": {"1": ["LR05"], "2": []}, "thresholds": [{"return_period": 1.5, "threshold_value": 750.5859679134564}, {"return_period": 2.0, "threshold_value": 844.3677500540222}, {"return_period": 5.0, "threshold_value": 1075.1620819816112}, {"return_period": 10.0, "threshold_value": 1227.9680117951257}, {"return_period": 20.0, "threshold_value": 1374.5431283208563}, {"return_period": 50.0, "threshold_value": 1564.2695818356037}, {"return_period": 100.0, "threshold_value": 1706.442860195532}, {"return_period": 200.0, "threshold_value": 1848.0973721445887}, {"return_period": 500.0, "threshold_value": 2034.9836026273404}]}, {"station_code": "G5111", "station_name": "Mano Kongo 01Ma003", "lat": 7.328, "lon": -11.143, "pcodes": {"1": ["LR05"], "2": []}, "thresholds": [{"return_period": 1.5, "threshold_value": 750.5859679134564}, {"return_period": 2.0, "threshold_value": 844.3677500540222}, {"return_period": 5.0, "threshold_value": 1075.1620819816112}, {"return_period": 10.0, "threshold_value": 1227.9680117951257}, {"return_period": 20.0, "threshold_value": 1374.5431283208563}, {"return_period": 50.0, "threshold_value": 1564.2695818356037}, {"return_period": 100.0, "threshold_value": 1706.442860195532}, {"return_period": 200.0, "threshold_value": 1848.0973721445887}, {"return_period": 500.0, "threshold_value": 2034.9836026273404}]}, {"station_code": "G4952", "station_name": "St.Paul River At Haindi 04Sp001", "lat": 6.90211, "lon": -10.36175, "pcodes": {"1": ["LR02", "LR01", "LR08", "LR03", "LR11"], "2": []}, "thresholds": [{"return_period": 1.5, "threshold_value": 4.048998830480402}, {"return_period": 2.0, "threshold_value": 4.513124058090853}, {"return_period": 5.0, "threshold_value": 5.655323207991206}, {"return_period": 10.0, "threshold_value": 6.4115584312526215}, {"return_period": 20.0, "threshold_value": 7.136957413515157}, {"return_period": 50.0, "threshold_value": 8.075911988821382}, {"return_period": 100.0, "threshold_value": 8.779526312123764}, {"return_period": 200.0, "threshold_value": 9.480573264951556}, {"return_period": 500.0, "threshold_value": 10.40547160107037}]}, {"station_code": "G4952", "station_name": "St.Paul River At Haindi 04Sp001", "lat": 6.90211, "lon": -10.36175, "pcodes": {"1": ["LR02", "LR01", "LR08", "LR03", "LR11"], "2": []}, "thresholds": [{"return_period": 1.5, "threshold_value": 4.048998830480402}, {"return_period": 2.0, "threshold_value": 4.513124058090853}, {"return_period": 5.0, "threshold_value": 5.655323207991206}, {"return_period": 10.0, "threshold_value": 6.4115584312526215}, {"return_period": 20.0, "threshold_value": 7.136957413515157}, {"return_period": 50.0, "threshold_value": 8.075911988821382}, {"return_period": 100.0, "threshold_value": 8.779526312123764}, {"return_period": 200.0, "threshold_value": 9.480573264951556}, {"return_period": 500.0, "threshold_value": 10.40547160107037}]}, {"station_code": "G4952", "station_name": "St.Paul River At Haindi 04Sp001", "lat": 6.90211, "lon": -10.36175, "pcodes": {"1": ["LR02", "LR01", "LR08", "LR03", "LR11"], "2": []}, "thresholds": [{"return_period": 1.5, "threshold_value": 4.048998830480402}, {"return_period": 2.0, "threshold_value": 4.513124058090853}, {"return_period": 5.0, "threshold_value": 5.655323207991206}, {"return_period": 10.0, "threshold_value": 6.4115584312526215}, {"return_period": 20.0, "threshold_value": 7.136957413515157}, {"return_period": 50.0, "threshold_value": 8.075911988821382}, {"return_period": 100.0, "threshold_value": 8.779526312123764}, {"return_period": 200.0, "threshold_value": 9.480573264951556}, {"return_period": 500.0, "threshold_value": 10.40547160107037}]}, {"station_code": "G4952", "station_name": "St.Paul River At Haindi 04Sp001", "lat": 6.90211, "lon": -10.36175, "pcodes": {"1": ["LR02", "LR01", "LR08", "LR03", "LR11"], "2": []}, "thresholds": [{"return_period": 1.5, "threshold_value": 4.048998830480402}, {"return_period": 2.0, "threshold_value": 4.513124058090853}, {"return_period": 5.0, "threshold_value": 5.655323207991206}, {"return_period": 10.0, "threshold_value": 6.4115584312526215}, {"return_period": 20.0, "threshold_value": 7.136957413515157}, {"return_period": 50.0, "threshold_value": 8.075911988821382}, {"return_period": 100.0, "threshold_value": 8.779526312123764}, {"return_period": 200.0, "threshold_value": 9.480573264951556}, {"return_period": 500.0, "threshold_value": 10.40547160107037}]}, {"station_code": "G4952", "station_name": "St.Paul River At Haindi 04Sp001", "lat": 6.90211, "lon": -10.36175, "pcodes": {"1": ["LR02", "LR01", "LR08", "LR03", "LR11"], "2": []}, "thresholds": [{"return_period": 1.5, "threshold_value": 4.048998830480402}, {"return_period": 2.0, "threshold_value": 4.513124058090853}, {"return_period": 5.0, "threshold_value": 5.655323207991206}, {"return_period": 10.0, "threshold_value": 6.4115584312526215}, {"return_period": 20.0, "threshold_value": 7.136957413515157}, {"return_period": 50.0, "threshold_value": 8.075911988821382}, {"return_period": 100.0, "threshold_value": 8.779526312123764}, {"return_period": 200.0, "threshold_value": 9.480573264951556}, {"return_period": 500.0, "threshold_value": 10.40547160107037}]}, {"station_code": "G4952", "station_name": "St.Paul River At Haindi 04Sp001", "lat": 6.90211, "lon": -10.36175, "pcodes": {"1": ["LR02", "LR01", "LR08", "LR03", "LR11"], "2": []}, "thresholds": [{"return_period": 1.5, "threshold_value": 4.048998830480402}, {"return_period": 2.0, "threshold_value": 4.513124058090853}, {"return_period": 5.0, "threshold_value": 5.655323207991206}, {"return_period": 10.0, "threshold_value": 6.4115584312526215}, {"return_period": 20.0, "threshold_value": 7.136957413515157}, {"return_period": 50.0, "threshold_value": 8.075911988821382}, {"return_period": 100.0, "threshold_value": 8.779526312123764}, {"return_period": 200.0, "threshold_value": 9.480573264951556}, {"return_period": 500.0, "threshold_value": 10.40547160107037}]}, {"station_code": "G4952", "station_name": "St.Paul River At Haindi 04Sp001", "lat": 6.90211, "lon": -10.36175, "pcodes": {"1": ["LR02", "LR01", "LR08", "LR03", "LR11"], "2": []}, "thresholds": [{"return_period": 1.5, "threshold_value": 4.048998830480402}, {"return_period": 2.0, "threshold_value": 4.513124058090853}, {"return_period": 5.0, "threshold_value": 5.655323207991206}, {"return_period": 10.0, "threshold_value": 6.4115584312526215}, {"return_period": 20.0, "threshold_value": 7.136957413515157}, {"return_period": 50.0, "threshold_value": 8.075911988821382}, {"return_period": 100.0, "threshold_value": 8.779526312123764}, {"return_period": 200.0, "threshold_value": 9.480573264951556}, {"return_period": 500.0, "threshold_value": 10.40547160107037}]}, {"station_code": "G1114", "station_name": "Tate", "lat": 4.38, "lon": -7.59, "pcodes": {"1": ["LR10", "LR06", "LR13"], "2": []}, "thresholds": [{"return_period": 1.5, "threshold_value": 1912.840758978593}, {"return_period": 2.0, "threshold_value": 2308.1394526953977}, {"return_period": 5.0, "threshold_value": 3280.9584357199847}, {"return_period": 10.0, "threshold_value": 3925.0492502550187}, {"return_period": 20.0, "threshold_value": 4542.8766232427115}, {"return_period": 50.0, "threshold_value": 5342.590784416245}, {"return_period": 100.0, "threshold_value": 5941.864011415471}, {"return_period": 200.0, "threshold_value": 6538.950591073595}, {"return_period": 500.0, "threshold_value": 7326.692955286293}]}, {"station_code": "G1114", "station_name": "Tate", "lat": 4.38, "lon": -7.59, "pcodes": {"1": ["LR10", "LR06", "LR13"], "2": []}, "thresholds": [{"return_period": 1.5, "threshold_value": 1912.840758978593}, {"return_period": 2.0, "threshold_value": 2308.1394526953977}, {"return_period": 5.0, "threshold_value": 3280.9584357199847}, {"return_period": 10.0, "threshold_value": 3925.0492502550187}, {"return_period": 20.0, "threshold_value": 4542.8766232427115}, {"return_period": 50.0, "threshold_value": 5342.590784416245}, {"return_period": 100.0, "threshold_value": 5941.864011415471}, {"return_period": 200.0, "threshold_value": 6538.950591073595}, {"return_period": 500.0, "threshold_value": 7326.692955286293}]}, {"station_code": "G1114", "station_name": "Tate", "lat": 4.38, "lon": -7.59, "pcodes": {"1": ["LR10", "LR06", "LR13"], "2": []}, "thresholds": [{"return_period": 1.5, "threshold_value": 1912.840758978593}, {"return_period": 2.0, "threshold_value": 2308.1394526953977}, {"return_period": 5.0, "threshold_value": 3280.9584357199847}, {"return_period": 10.0, "threshold_value": 3925.0492502550187}, {"return_period": 20.0, "threshold_value": 4542.8766232427115}, {"return_period": 50.0, "threshold_value": 5342.590784416245}, {"return_period": 100.0, "threshold_value": 5941.864011415471}, {"return_period": 200.0, "threshold_value": 6538.950591073595}, {"return_period": 500.0, "threshold_value": 7326.692955286293}]}, {"station_code": "G1114", "station_name": "Tate", "lat": 4.38, "lon": -7.59, "pcodes": {"1": ["LR10", "LR06", "LR13"], "2": []}, "thresholds": [{"return_period": 1.5, "threshold_value": 1912.840758978593}, {"return_period": 2.0, "threshold_value": 2308.1394526953977}, {"return_period": 5.0, "threshold_value": 3280.9584357199847}, {"return_period": 10.0, "threshold_value": 3925.0492502550187}, {"return_period": 20.0, "threshold_value": 4542.8766232427115}, {"return_period": 50.0, "threshold_value": 5342.590784416245}, {"return_period": 100.0, "threshold_value": 5941.864011415471}, {"return_period": 200.0, "threshold_value": 6538.950591073595}, {"return_period": 500.0, "threshold_value": 7326.692955286293}]}, {"station_code": "G1114", "station_name": "Tate", "lat": 4.38, "lon": -7.59, "pcodes": {"1": ["LR10", "LR06", "LR13"], "2": []}, "thresholds": [{"return_period": 1.5, "threshold_value": 1912.840758978593}, {"return_period": 2.0, "threshold_value": 2308.1394526953977}, {"return_period": 5.0, "threshold_value": 3280.9584357199847}, {"return_period": 10.0, "threshold_value": 3925.0492502550187}, {"return_period": 20.0, "threshold_value": 4542.8766232427115}, {"return_period": 50.0, "threshold_value": 5342.590784416245}, {"return_period": 100.0, "threshold_value": 5941.864011415471}, {"return_period": 200.0, "threshold_value": 6538.950591073595}, {"return_period": 500.0, "threshold_value": 7326.692955286293}]}, {"station_code": "G1114", "station_name": "Tate", "lat": 4.38, "lon": -7.59, "pcodes": {"1": ["LR10", "LR06", "LR13"], "2": []}, "thresholds": [{"return_period": 1.5, "threshold_value": 1912.840758978593}, {"return_period": 2.0, "threshold_value": 2308.1394526953977}, {"return_period": 5.0, "threshold_value": 3280.9584357199847}, {"return_period": 10.0, "threshold_value": 3925.0492502550187}, {"return_period": 20.0, "threshold_value": 4542.8766232427115}, {"return_period": 50.0, "threshold_value": 5342.590784416245}, {"return_period": 100.0, "threshold_value": 5941.864011415471}, {"return_period": 200.0, "threshold_value": 6538.950591073595}, {"return_period": 500.0, "threshold_value": 7326.692955286293}]}, {"station_code": "G1114", "station_name": "Tate", "lat": 4.38, "lon": -7.59, "pcodes": {"1": ["LR10", "LR06", "LR13"], "2": []}, "thresholds": [{"return_period": 1.5, "threshold_value": 1912.840758978593}, {"return_period": 2.0, "threshold_value": 2308.1394526953977}, {"return_period": 5.0, "threshold_value": 3280.9584357199847}, {"return_period": 10.0, "threshold_value": 3925.0492502550187}, {"return_period": 20.0, "threshold_value": 4542.8766232427115}, {"return_period": 50.0, "threshold_value": 5342.590784416245}, {"return_period": 100.0, "threshold_value": 5941.864011415471}, {"return_period": 200.0, "threshold_value": 6538.950591073595}, {"return_period": 500.0, "threshold_value": 7326.692955286293}]}, {"station_code": "G5087", "station_name": "St.John River At Mount Finlay 06Sj002", "lat": 6.084, "lon": -9.87, "pcodes": {"1": ["LR14", "LR12", "LR02", "LR04"], "2": []}, "thresholds": [{"return_period": 1.5, "threshold_value": 1140.1262878543605}, {"return_period": 2.0, "threshold_value": 1294.1478713329257}, {"return_period": 5.0, "threshold_value": 1673.190662480618}, {"return_period": 10.0, "threshold_value": 1924.1499718219115}, {"return_period": 20.0, "threshold_value": 2164.87616651088}, {"return_period": 50.0, "threshold_value": 2476.471533234815}, {"return_period": 100.0, "threshold_value": 2709.9684124955793}, {"return_period": 200.0, "threshold_value": 2942.6133008660645}, {"return_period": 500.0, "threshold_value": 3249.544055350444}]}, {"station_code": "G5087", "station_name": "St.John River At Mount Finlay 06Sj002", "lat": 6.084, "lon": -9.87, "pcodes": {"1": ["LR14", "LR12", "LR02", "LR04"], "2": []}, "thresholds": [{"return_period": 1.5, "threshold_value": 1140.1262878543605}, {"return_period": 2.0, "threshold_value": 1294.1478713329257}, {"return_period": 5.0, "threshold_value": 1673.190662480618}, {"return_period": 10.0, "threshold_value": 1924.1499718219115}, {"return_period": 20.0, "threshold_value": 2164.87616651088}, {"return_period": 50.0, "threshold_value": 2476.471533234815}, {"return_period": 100.0, "threshold_value": 2709.9684124955793}, {"return_period": 200.0, "threshold_value": 2942.6133008660645}, {"return_period": 500.0, "threshold_value": 3249.544055350444}]}, {"station_code": "G5087", "station_name": "St.John River At Mount Finlay 06Sj002", "lat": 6.084, "lon": -9.87, "pcodes": {"1": ["LR14", "LR12", "LR02", "LR04"], "2": []}, "thresholds": [{"return_period": 1.5, "threshold_value": 1140.1262878543605}, {"return_period": 2.0, "threshold_value": 1294.1478713329257}, {"return_period": 5.0, "threshold_value": 1673.190662480618}, {"return_period": 10.0, "threshold_value": 1924.1499718219115}, {"return_period": 20.0, "threshold_value": 2164.87616651088}, {"return_period": 50.0, "threshold_value": 2476.471533234815}, {"return_period": 100.0, "threshold_value": 2709.9684124955793}, {"return_period": 200.0, "threshold_value": 2942.6133008660645}, {"return_period": 500.0, "threshold_value": 3249.544055350444}]}, {"station_code": "G5087", "station_name": "St.John River At Mount Finlay 06Sj002", "lat": 6.084, "lon": -9.87, "pcodes": {"1": ["LR14", "LR12", "LR02", "LR04"], "2": []}, "thresholds": [{"return_period": 1.5, "threshold_value": 1140.1262878543605}, {"return_period": 2.0, "threshold_value": 1294.1478713329257}, {"return_period": 5.0, "threshold_value": 1673.190662480618}, {"return_period": 10.0, "threshold_value": 1924.1499718219115}, {"return_period": 20.0, "threshold_value": 2164.87616651088}, {"return_period": 50.0, "threshold_value": 2476.471533234815}, {"return_period": 100.0, "threshold_value": 2709.9684124955793}, {"return_period": 200.0, "threshold_value": 2942.6133008660645}, {"return_period": 500.0, "threshold_value": 3249.544055350444}]}, {"station_code": "G5087", "station_name": "St.John River At Mount Finlay 06Sj002", "lat": 6.084, "lon": -9.87, "pcodes": {"1": ["LR14", "LR12", "LR02", "LR04"], "2": []}, "thresholds": [{"return_period": 1.5, "threshold_value": 1140.1262878543605}, {"return_period": 2.0, "threshold_value": 1294.1478713329257}, {"return_period": 5.0, "threshold_value": 1673.190662480618}, {"return_period": 10.0, "threshold_value": 1924.1499718219115}, {"return_period": 20.0, "threshold_value": 2164.87616651088}, {"return_period": 50.0, "threshold_value": 2476.471533234815}, {"return_period": 100.0, "threshold_value": 2709.9684124955793}, {"return_period": 200.0, "threshold_value": 2942.6133008660645}, {"return_period": 500.0, "threshold_value": 3249.544055350444}]}, {"station_code": "G5087", "station_name": "St.John River At Mount Finlay 06Sj002", "lat": 6.084, "lon": -9.87, "pcodes": {"1": ["LR14", "LR12", "LR02", "LR04"], "2": []}, "thresholds": [{"return_period": 1.5, "threshold_value": 1140.1262878543605}, {"return_period": 2.0, "threshold_value": 1294.1478713329257}, {"return_period": 5.0, "threshold_value": 1673.190662480618}, {"return_period": 10.0, "threshold_value": 1924.1499718219115}, {"return_period": 20.0, "threshold_value": 2164.87616651088}, {"return_period": 50.0, "threshold_value": 2476.471533234815}, {"return_period": 100.0, "threshold_value": 2709.9684124955793}, {"return_period": 200.0, "threshold_value": 2942.6133008660645}, {"return_period": 500.0, "threshold_value": 3249.544055350444}]}, {"station_code": "G5087", "station_name": "St.John River At Mount Finlay 06Sj002", "lat": 6.084, "lon": -9.87, "pcodes": {"1": ["LR14", "LR12", "LR02", "LR04"], "2": []}, "thresholds": [{"return_period": 1.5, "threshold_value": 1140.1262878543605}, {"return_period": 2.0, "threshold_value": 1294.1478713329257}, {"return_period": 5.0, "threshold_value": 1673.190662480618}, {"return_period": 10.0, "threshold_value": 1924.1499718219115}, {"return_period": 20.0, "threshold_value": 2164.87616651088}, {"return_period": 50.0, "threshold_value": 2476.471533234815}, {"return_period": 100.0, "threshold_value": 2709.9684124955793}, {"return_period": 200.0, "threshold_value": 2942.6133008660645}, {"return_period": 500.0, "threshold_value": 3249.544055350444}]}, {"station_code": "G5108", "station_name": "St.John River At Frank Diggs 06Sj001", "lat": 6.466, "lon": -9.526, "pcodes": {"1": ["LR14", "LR12", "LR02", "LR04"], "2": []}, "thresholds": [{"return_period": 1.5, "threshold_value": 745.7720936074174}, {"return_period": 2.0, "threshold_value": 827.5225148360212}, {"return_period": 5.0, "threshold_value": 1028.7080054676107}, {"return_period": 10.0, "threshold_value": 1161.9103059928834}, {"return_period": 20.0, "threshold_value": 1289.6811506506438}, {"return_period": 50.0, "threshold_value": 1455.067403065767}, {"return_period": 100.0, "threshold_value": 1579.0011258857794}, {"return_period": 200.0, "threshold_value": 1702.4826353692565}, {"return_period": 500.0, "threshold_value": 1865.3930398750194}]}, {"station_code": "G5108", "station_name": "St.John River At Frank Diggs 06Sj001", "lat": 6.466, "lon": -9.526, "pcodes": {"1": ["LR14", "LR12", "LR02", "LR04"], "2": []}, "thresholds": [{"return_period": 1.5, "threshold_value": 745.7720936074174}, {"return_period": 2.0, "threshold_value": 827.5225148360212}, {"return_period": 5.0, "threshold_value": 1028.7080054676107}, {"return_period": 10.0, "threshold_value": 1161.9103059928834}, {"return_period": 20.0, "threshold_value": 1289.6811506506438}, {"return_period": 50.0, "threshold_value": 1455.067403065767}, {"return_period": 100.0, "threshold_value": 1579.0011258857794}, {"return_period": 200.0, "threshold_value": 1702.4826353692565}, {"return_period": 500.0, "threshold_value": 1865.3930398750194}]}, {"station_code": "G5108", "station_name": "St.John River At Frank Diggs 06Sj001", "lat": 6.466, "lon": -9.526, "pcodes": {"1": ["LR14", "LR12", "LR02", "LR04"], "2": []}, "thresholds": [{"return_period": 1.5, "threshold_value": 745.7720936074174}, {"return_period": 2.0, "threshold_value": 827.5225148360212}, {"return_period": 5.0, "threshold_value": 1028.7080054676107}, {"return_period": 10.0, "threshold_value": 1161.9103059928834}, {"return_period": 20.0, "threshold_value": 1289.6811506506438}, {"return_period": 50.0, "threshold_value": 1455.067403065767}, {"return_period": 100.0, "threshold_value": 1579.0011258857794}, {"return_period": 200.0, "threshold_value": 1702.4826353692565}, {"return_period": 500.0, "threshold_value": 1865.3930398750194}]}, {"station_code": "G5108", "station_name": "St.John River At Frank Diggs 06Sj001", "lat": 6.466, "lon": -9.526, "pcodes": {"1": ["LR14", "LR12", "LR02", "LR04"], "2": []}, "thresholds": [{"return_period": 1.5, "threshold_value": 745.7720936074174}, {"return_period": 2.0, "threshold_value": 827.5225148360212}, {"return_period": 5.0, "threshold_value": 1028.7080054676107}, {"return_period": 10.0, "threshold_value": 1161.9103059928834}, {"return_period": 20.0, "threshold_value": 1289.6811506506438}, {"return_period": 50.0, "threshold_value": 1455.067403065767}, {"return_period": 100.0, "threshold_value": 1579.0011258857794}, {"return_period": 200.0, "threshold_value": 1702.4826353692565}, {"return_period": 500.0, "threshold_value": 1865.3930398750194}]}, {"station_code": "G5108", "station_name": "St.John River At Frank Diggs 06Sj001", "lat": 6.466, "lon": -9.526, "pcodes": {"1": ["LR14", "LR12", "LR02", "LR04"], "2": []}, "thresholds": [{"return_period": 1.5, "threshold_value": 745.7720936074174}, {"return_period": 2.0, "threshold_value": 827.5225148360212}, {"return_period": 5.0, "threshold_value": 1028.7080054676107}, {"return_period": 10.0, "threshold_value": 1161.9103059928834}, {"return_period": 20.0, "threshold_value": 1289.6811506506438}, {"return_period": 50.0, "threshold_value": 1455.067403065767}, {"return_period": 100.0, "threshold_value": 1579.0011258857794}, {"return_period": 200.0, "threshold_value": 1702.4826353692565}, {"return_period": 500.0, "threshold_value": 1865.3930398750194}]}, {"station_code": "G5108", "station_name": "St.John River At Frank Diggs 06Sj001", "lat": 6.466, "lon": -9.526, "pcodes": {"1": ["LR14", "LR12", "LR02", "LR04"], "2": []}, "thresholds": [{"return_period": 1.5, "threshold_value": 745.7720936074174}, {"return_period": 2.0, "threshold_value": 827.5225148360212}, {"return_period": 5.0, "threshold_value": 1028.7080054676107}, {"return_period": 10.0, "threshold_value": 1161.9103059928834}, {"return_period": 20.0, "threshold_value": 1289.6811506506438}, {"return_period": 50.0, "threshold_value": 1455.067403065767}, {"return_period": 100.0, "threshold_value": 1579.0011258857794}, {"return_period": 200.0, "threshold_value": 1702.4826353692565}, {"return_period": 500.0, "threshold_value": 1865.3930398750194}]}, {"station_code": "G5108", "station_name": "St.John River At Frank Diggs 06Sj001", "lat": 6.466, "lon": -9.526, "pcodes": {"1": ["LR14", "LR12", "LR02", "LR04"], "2": []}, "thresholds": [{"return_period": 1.5, "threshold_value": 745.7720936074174}, {"return_period": 2.0, "threshold_value": 827.5225148360212}, {"return_period": 5.0, "threshold_value": 1028.7080054676107}, {"return_period": 10.0, "threshold_value": 1161.9103059928834}, {"return_period": 20.0, "threshold_value": 1289.6811506506438}, {"return_period": 50.0, "threshold_value": 1455.067403065767}, {"return_period": 100.0, "threshold_value": 1579.0011258857794}, {"return_period": 200.0, "threshold_value": 1702.4826353692565}, {"return_period": 500.0, "threshold_value": 1865.3930398750194}]}]